{
  "signal_id": "ARONSON_DRY_0_1",
  "book_id": "ARONSON",
  "dsl_rule": {
    "signal_id": "ARONSON_DRY_0_1",
    "entry_long": [
      {
        "left": "close",
        "operator": ">",
        "right": "dc_upper"
      },
      {
        "left": "close",
        "operator": ">",
        "right": "prev_high"
      }
    ],
    "entry_short": [
      {
        "left": "close",
        "operator": "<",
        "right": "dc_lower"
      },
      {
        "left": "close",
        "operator": "<",
        "right": "prev_low"
      }
    ],
    "exit_long": [
      {
        "left": "close",
        "operator": "<",
        "right": "dc_middle"
      }
    ],
    "exit_short": [
      {
        "left": "close",
        "operator": ">",
        "right": "dc_middle"
      }
    ],
    "entry_logic": "AND",
    "exit_logic": "OR",
    "stop_loss_pct": 2.0,
    "hold_days_max": 10,
    "direction": "BOTH",
    "target_regime": [
      "TRENDING_UP",
      "TRENDING_DOWN"
    ],
    "untranslatable": false,
    "untranslatable_reason": null,
    "translation_notes": "Mapped 10-period channel breakout to Donchian channels (dc_upper, dc_lower, dc_middle) which represent high/low bands over a lookback period. Entry requires price breakout beyond channel boundary with confirmation on next candle (prev_high/prev_low comparison). Exit when price reverts to channel middle. Direction is context-dependent: long entries when breaking above, short entries when breaking below. No volume filter applied per signal specification."
  },
  "backtest_rule": {
    "backtestable": true,
    "entry_long": [
      {
        "indicator": "close",
        "op": ">",
        "value": "dc_upper"
      },
      {
        "indicator": "close",
        "op": ">",
        "value": "prev_high"
      }
    ],
    "entry_short": [
      {
        "indicator": "close",
        "op": "<",
        "value": "dc_lower"
      },
      {
        "indicator": "close",
        "op": "<",
        "value": "prev_low"
      }
    ],
    "exit_long": [
      {
        "indicator": "close",
        "op": "<",
        "value": "dc_middle"
      }
    ],
    "exit_short": [
      {
        "indicator": "close",
        "op": ">",
        "value": "dc_middle"
      }
    ],
    "regime_filter": [
      "TRENDING_UP",
      "TRENDING_DOWN"
    ],
    "hold_days": 10,
    "stop_loss_pct": 0.02,
    "take_profit_pct": 0,
    "direction": "BOTH",
    "reason": "Mapped 10-period channel breakout to Donchian channels (dc_upper, dc_lower, dc_middle) which represent high/low bands over a lookback period. Entry requires price breakout beyond channel boundary with confirmation on next candle (prev_high/prev_low comparison). Exit when price reverts to channel middle. Direction is context-dependent: long entries when breaking above, short entries when breaking below. No volume filter applied per signal specification."
  },
  "source_rule_text": "A trader should enter positions when a channel breakout operator (CBO) identifies a trend direction in the price series with sufficient timeliness to generate profits."
}