{
  "signal_id": "THARP_DRY_17_2",
  "book_id": "THARP",
  "signal_type": "POSITION_SIZING",
  "sizing_rule": {
    "signal_type": "POSITION_SIZING",
    "sizing_method": "DRAWDOWN_SCALED",
    "base_risk_pct": null,
    "r_multiple_target": null,
    "r_multiple_stop": null,
    "scale_up_multiplier": null,
    "scale_down_multiplier": 0.75,
    "scale_factor": null,
    "trigger_condition": {
      "metric": "equity_drawdown_from_peak",
      "threshold": 0.2,
      "direction": "below"
    },
    "max_risk_pct": null,
    "min_risk_pct": null,
    "applies_to": "ALL",
    "confidence": "HIGH",
    "note": "Reduce position size by 25% when cumulative equity falls to 80% of recent peak (20% drawdown). Metric derived from cumulative win/loss ratio deterioration over 50-trade lookback period. Signals strategy review or capital preservation action.",
    "untranslatable": false,
    "untranslatable_reason": null
  }
}