{
  "signal_id": "THARP_DRY_32_0",
  "book_id": "THARP",
  "signal_type": "POSITION_SIZING",
  "sizing_rule": {
    "signal_type": "POSITION_SIZING",
    "sizing_method": "FIXED_FRACTIONAL",
    "base_risk_pct": 0.005,
    "r_multiple_target": null,
    "r_multiple_stop": null,
    "scale_up_multiplier": null,
    "scale_down_multiplier": null,
    "scale_factor": null,
    "trigger_condition": {
      "metric": "account_size",
      "threshold": 50000,
      "direction": "below"
    },
    "max_risk_pct": 0.005,
    "min_risk_pct": null,
    "applies_to": "ALL",
    "confidence": "MEDIUM",
    "note": "For accounts under $50k, use reduced contract sizes (0.25 contracts or micro-lots) corresponding to 0.5% account risk limit per trade. This implements fixed fractional risk scaled for limited capital.",
    "untranslatable": false,
    "untranslatable_reason": null
  },
  "source_rule_text": "Scale position size to account size: traders with limited capital should trade smaller contract quantities to manage risk relative to their available funds."
}