{
  "signal_id": "VINCE_DRY_6",
  "book_id": "VINCE",
  "signal_type": "POSITION_SIZING",
  "sizing_rule": {
    "signal_type": "POSITION_SIZING",
    "sizing_method": "VOLATILITY_SCALED",
    "base_risk_pct": null,
    "r_multiple_target": null,
    "r_multiple_stop": null,
    "scale_up_multiplier": null,
    "scale_down_multiplier": null,
    "scale_factor": null,
    "trigger_condition": {
      "metric": "covariance_weighted_portfolio_allocation",
      "threshold": null,
      "direction": "inverse"
    },
    "max_risk_pct": null,
    "min_risk_pct": null,
    "applies_to": "ALL",
    "confidence": "MEDIUM",
    "note": "Portfolio position weights (Xi) determined by inverse scaling of individual security standard deviations (Si) and covariances (COVi,j = Ri,j \u00d7 Si \u00d7 Sj). Higher volatility securities receive smaller allocations; lower volatility securities receive larger allocations. This is Modern Portfolio Theory variance minimization weighting.",
    "untranslatable": false,
    "untranslatable_reason": null
  },
  "source_rule_text": "Position sizing for multi-security portfolios should be weighted (Xi) based on the standard deviation and covariance of expected returns between securities to optimize portfolio variance."
}