{
  "signal_id": "VINCE_DRY_8",
  "book_id": "VINCE",
  "signal_type": "POSITION_SIZING",
  "sizing_rule": {
    "signal_type": "POSITION_SIZING",
    "sizing_method": "OPTIMAL_F",
    "base_risk_pct": null,
    "r_multiple_target": null,
    "r_multiple_stop": null,
    "scale_up_multiplier": null,
    "scale_down_multiplier": null,
    "scale_factor": null,
    "trigger_condition": null,
    "max_risk_pct": null,
    "min_risk_pct": null,
    "applies_to": "ALL",
    "confidence": "HIGH",
    "note": "Apply full optimal f calculation to active equity allocation subset (e.g., 20% of total account). Position size = Optimal f \u00d7 (Active Equity % of Total Account). Maintain inactive portion for stability and withdraw constant percentage monthly.",
    "untranslatable": false,
    "untranslatable_reason": null
  },
  "source_rule_text": "Use full optimal f on an active equity allocation (e.g., 20% of total account), while maintaining an inactive portion, and withdraw a constant percentage of total account equity each month"
}