{
  "signal_id": "BULKOWSKI_CUP_HANDLE",
  "entry_long": [],
  "entry_short": [],
  "exit_long": [],
  "exit_short": [],
  "entry_logic": "AND",
  "exit_logic": "AND",
  "stop_loss_pct": 2.0,
  "hold_days_max": 10,
  "direction": "BOTH",
  "target_regime": [
    "ANY"
  ],
  "untranslatable": true,
  "untranslatable_reason": "Cup-with-Handle pattern requires multi-bar structural analysis (cup formation identification, handle retracement depth relative to cup midpoint). Available indicators cannot precisely detect: (1) the two outer peaks forming proper cup geometry, (2) the cup midpoint calculation for handle validation, (3) excessive drop below midpoint threshold. Pattern requires pattern recognition beyond single-bar indicator conditions.",
  "translation_notes": null
}