{
  "signal_id": "BULKOWSKI_EXHAUSTION_GAP",
  "entry_long": [],
  "entry_short": [],
  "exit_long": [],
  "exit_short": [],
  "entry_logic": "AND",
  "exit_logic": "AND",
  "stop_loss_pct": 2.0,
  "hold_days_max": 10,
  "direction": "BOTH",
  "target_regime": [
    "ANY"
  ],
  "untranslatable": true,
  "untranslatable_reason": "Exhaustion Gap pattern requires multi-bar trend analysis to identify the true midway point of a price move and directional context. The pattern definition references 'midway point of a price move' which requires lookback analysis to measure prior trend length\u2014not available via single-bar indicator conditions. Gap direction alone (entry conditions converted) is insufficient; the 'exhaustion' characteristic requires measuring prior move magnitude relative to post-gap continuation, which exceeds available indicator scope.",
  "translation_notes": null
}