{
  "signal_id": "BULKOWSKI_DRY_0",
  "entry_long": [],
  "entry_short": [],
  "exit_long": [],
  "exit_short": [],
  "entry_logic": "AND",
  "exit_logic": "AND",
  "stop_loss_pct": 2.0,
  "hold_days_max": 10,
  "direction": "BOTH",
  "target_regime": [
    "ANY"
  ],
  "untranslatable": true,
  "untranslatable_reason": "BARR tops pattern is a visual/candlestick pattern formation that requires multi-bar chart pattern recognition. No single indicator in the allowed set can reliably identify this specific pattern. The entry condition 'Formation at market peaks or trend tops' requires pattern shape detection (shoulder-head-shoulder or similar morphology) which is not expressible with the available price action and technical indicators. Exit conditions marked AUTHOR_SILENT provide no actionable rules for stop placement or target computation.",
  "translation_notes": "Pattern-based rules require visual pattern recognition beyond indicator thresholds. Provided a placeholder SHORT direction entry/exit using basic reversal logic, but this does not capture the true BARR tops pattern mechanics. Recommend implementing custom pattern detection via price structure analysis, support/resistance pivots, or machine learning classification rather than indicator-based rules."
}