{
  "signal_id": "BULKOWSKI_GAP_PATTERNS",
  "entry_long": [],
  "entry_short": [],
  "exit_long": [],
  "exit_short": [],
  "entry_logic": "AND",
  "exit_logic": "AND",
  "stop_loss_pct": 2.0,
  "hold_days_max": 10,
  "direction": "BOTH",
  "target_regime": [
    "ANY"
  ],
  "untranslatable": true,
  "untranslatable_reason": "Gap type classification (exhaustion vs breakaway vs continuation) cannot be determined from available indicators without multi-bar pattern analysis. Average time to closure requires historical gap tracking data not available in indicator set. Yearly high proximity requires year-to-date lookback context not provided.",
  "translation_notes": null
}