{
  "signal_id": "HILPISCH_DRY_9_0",
  "entry_long": [],
  "entry_short": [],
  "exit_long": [],
  "exit_short": [],
  "entry_logic": "AND",
  "exit_logic": "AND",
  "stop_loss_pct": 2.0,
  "hold_days_max": 10,
  "direction": "BOTH",
  "target_regime": [
    "ANY"
  ],
  "untranslatable": true,
  "untranslatable_reason": "Signal requires a rolling mean (momentum period) calculation that is not available as a pre-computed indicator in the allowed list. The allowed indicators do not include a configurable rolling mean of log returns. Additionally, position confirmation persistence (position_confirmation_bars threshold) cannot be expressed with the allowed operators and indicators.",
  "translation_notes": "Used log_returns as the primary indicator since the signal explicitly mentions 'log returns of mid-price'. However, the core requirement for a rolling mean over a momentum period cannot be translated without access to a rolling_mean indicator or similar. The threshold values for entry/exit and confirmation bars are marked as [THRESHOLD_NEEDED] in the original signal and require parameter specification. The crosses_above/crosses_below operators approximate the crossing logic mentioned in exit conditions."
}