{
  "signal_id": "KAUFMAN_DRY_21",
  "entry_long": [],
  "entry_short": [],
  "exit_long": [],
  "exit_short": [],
  "entry_logic": "AND",
  "exit_logic": "AND",
  "stop_loss_pct": 2.0,
  "hold_days_max": 10,
  "direction": "BOTH",
  "target_regime": [
    "ANY"
  ],
  "untranslatable": true,
  "untranslatable_reason": "Signal references undefined 'slow average' and 'fast average' without specifying which moving averages to use. Parameters marked AUTHOR_SILENT indicate the original source does not specify the calculation period or which MA types (SMA vs EMA) to apply. Used reasonable defaults (sma_50 for slow, sma_20 for fast) but this is an assumption. The phrase 'turns up/down' requires direction detection which assumes comparison to previous bar value.",
  "translation_notes": "Interpreted 'slow average is down' as slow MA below previous close; 'fast average turns up' as fast MA crossing above slow MA. 'Slow average turns down' interpreted as slow MA crossing below current price. 'Slow average turns up' interpreted as slow MA crossing above current price. Assigned default MAs (sma_50=slow, sma_20=fast) but recommend confirming with original Kaufman methodology specifications."
}