{
  "signal_id": "KAUFMAN_DRY_15",
  "entry_long": [],
  "entry_short": [],
  "exit_long": [],
  "exit_short": [],
  "entry_logic": "AND",
  "exit_logic": "AND",
  "stop_loss_pct": 2.0,
  "hold_days_max": 10,
  "direction": "BOTH",
  "target_regime": [
    "ANY"
  ],
  "untranslatable": true,
  "untranslatable_reason": "Signal requires calendar-based logic (4 days before month-end) which cannot be expressed using technical indicators from the allowed list. The exact entry timing is date-dependent, not price/indicator-dependent. No allowed indicator can directly reference calendar days or month positions.",
  "translation_notes": "The core signal intent is to buy near month-end to capture end-of-month buying pressure. This temporal requirement is incompatible with the technical indicator-based rule engine. A price-based proxy (close > sma_20) is provided as a basic uptrend confirmation, but this does not capture the calendar-specific timing that is central to the signal's hypothesis."
}