{
  "signal_id": "SCHWAGER_DRY_0_1",
  "entry_long": [],
  "entry_short": [],
  "exit_long": [],
  "exit_short": [],
  "entry_logic": "AND",
  "exit_logic": "AND",
  "stop_loss_pct": 2.0,
  "hold_days_max": 10,
  "direction": "BOTH",
  "target_regime": [
    "ANY"
  ],
  "untranslatable": true,
  "untranslatable_reason": "Signal requires detection of 'historical resistance level' and 'at least one prior test within last 30 bars' \u2014 these require multi-bar pattern recognition (swing high detection, resistance zone identification) not available in the allowed indicator set. The Pivot (r1) is used as a proxy for resistance, but true implementation requires lookback pattern analysis across 40 bars to identify dynamically-formed resistance zones, which exceeds the scope of single-bar technical indicators.",
  "translation_notes": "Attempted translation using pivot point r1 as a practical proxy for resistance level. Entry condition translates price crossing above resistance (r1) with volume confirmation above 20-bar historical average. Exit uses reversal below resistance. However, the core signal logic\u2014identifying previously-defended resistance through multiple tests\u2014cannot be fully expressed without custom pattern-matching logic or multi-bar state tracking."
}