{
  "signal_id": "SSRN_299107_6",
  "entry_long": [],
  "entry_short": [],
  "exit_long": [],
  "exit_short": [],
  "entry_logic": "AND",
  "exit_logic": "AND",
  "stop_loss_pct": 2.0,
  "hold_days_max": 10,
  "direction": "BOTH",
  "target_regime": [
    "ANY"
  ],
  "untranslatable": true,
  "untranslatable_reason": "Signal requires calculation of contemporaneous beta (\u03b2_0i), lagged beta (\u03b2_1i), and the cross-sectional condition (d > 0) comparing firm-level betas across the universe. These are multi-period, cross-sectional statistical measures that cannot be expressed using only the allowed point-in-time indicators (price, moving averages, RSI, ATR, etc.). Beta estimation requires factor returns and individual stock returns regression analysis over a lookback window, which is not available in the allowed indicator set.",
  "translation_notes": "The signal's core logic involves delayed market reactions based on beta characteristics. While we can approximate 'positive market movements' as returns > 0, the critical high-beta and lagged-beta selection criteria require econometric factor analysis unavailable in standard technical indicators. A practical workaround would require adding custom beta indicators (beta_contemporaneous, beta_lagged, beta_condition_d) to the allowed set."
}