{
  "signal_id": "SSRN_3323746_1",
  "entry_long": [],
  "entry_short": [],
  "exit_long": [],
  "exit_short": [],
  "entry_logic": "AND",
  "exit_logic": "AND",
  "stop_loss_pct": 2.0,
  "hold_days_max": 10,
  "direction": "BOTH",
  "target_regime": [
    "ANY"
  ],
  "untranslatable": true,
  "untranslatable_reason": "The signal references 'CCI (Commodity Channel Index)' which is NOT in the allowed indicators list. CCI is a specialized momentum oscillator that cannot be accurately substituted with available indicators (RSI, stoch, ADX, MACD). The exact CCI threshold for 'strong momentum' is also not specified in the excerpt. Additionally, the signal specifies ITM (In-The-Money) option contracts, which is a contract-level attribute not expressible in price/technical indicator conditions.",
  "translation_notes": "Attempted partial translation using price action (close > pivot) as a weak proxy for momentum, with 100%+ return target and 14-day holding period as specified. However, without CCI and proper option moneyness filtering, this translation does not accurately capture the original signal intent. Backtest engine should use CCI indicator separately or signal is untranslatable."
}