{
  "signal_id": "THARP_DRY_15_0",
  "entry_long": [],
  "entry_short": [],
  "exit_long": [],
  "exit_short": [],
  "entry_logic": "AND",
  "exit_logic": "AND",
  "stop_loss_pct": 2.0,
  "hold_days_max": 10,
  "direction": "BOTH",
  "target_regime": [
    "ANY"
  ],
  "untranslatable": true,
  "untranslatable_reason": "Not a sizing rule. This signal describes entry conditions and pattern recognition for seasonal trading. It contains no position sizing methodology, risk allocation percentage, capital fraction rules, volatility scaling, Kelly calculations, or any other position sizing directive. It is purely an entry filter based on historical pattern confirmation and price action proximity to seasonal inflection points.",
  "translation_notes": null
}