{
  "signal_id": "THARP_DRY_14_0",
  "entry_long": [],
  "entry_short": [],
  "exit_long": [],
  "exit_short": [],
  "entry_logic": "AND",
  "exit_logic": "AND",
  "stop_loss_pct": 2.0,
  "hold_days_max": 10,
  "direction": "BOTH",
  "target_regime": [
    "ANY"
  ],
  "untranslatable": true,
  "untranslatable_reason": "Philosophy statement without specific sizing parameters. The rule emphasizes that position sizing is a required component of a complete system but does not specify a sizing method, percentage, or trigger condition. The parameters provided (max_risk_per_trade_pct: 1.0, stop_loss_atr_multiple: 1.5, position_size_kelly_fraction: 0.25) are illustrative examples rather than explicit sizing rules extracted from the text.",
  "translation_notes": null
}