{
  "signal_id": "VINCE_DRY_7",
  "entry_long": [],
  "entry_short": [],
  "exit_long": [],
  "exit_short": [],
  "entry_logic": "AND",
  "exit_logic": "AND",
  "stop_loss_pct": 2.0,
  "hold_days_max": 10,
  "direction": "BOTH",
  "target_regime": [
    "ANY"
  ],
  "untranslatable": true,
  "untranslatable_reason": "Not a sizing rule. This is a methodological instruction for calculating correlation inputs used in sizing decisions, not a rule that specifies how to size positions. It describes DATA PREPARATION (use daily equity changes vs prices) for correlation calculation, not position sizing mechanics (no allocation %, leverage multiplier, or sizing trigger specified).",
  "translation_notes": null
}